enochecker3/__init__.py
enochecker3/chaindb.py
enochecker3/enochecker.py
enochecker3/logging.py
enochecker3/py.typed
enochecker3/types.py
enochecker3/utils.py
tests/__init__.py
tests/conftest.py
tests/test_chaindb.py
tests/test_dependency_injection.py
tests/test_utils.py
tests/test_variant_ids.py
enochecker3-0.10.0.dist-info/LICENSE
enochecker3-0.10.0.dist-info/METADATA
enochecker3-0.10.0.dist-info/WHEEL
enochecker3-0.10.0.dist-info/top_level.txt
enochecker3-0.10.0.dist-info/RECORD
