Metadata-Version: 2.2
Name: enochecker3
Version: 0.10.0
Summary: FastAPI based library for building async python checkers for the EnoEngine A/D CTF Framework
Home-page: https://github.com/ENOWARS/enochecker3
Author: ldruschk
Author-email: ldruschk@posteo.de
Classifier: Development Status :: 3 - Alpha
Classifier: License :: OSI Approved :: MIT License
Classifier: Programming Language :: Python :: 3.9
Classifier: Programming Language :: Python :: 3.10
Classifier: Programming Language :: Python :: 3.11
Classifier: Programming Language :: Python :: 3.12
Classifier: Programming Language :: Python :: 3.13
Requires-Python: >=3.9
License-File: LICENSE
Requires-Dist: httpx<0.29.0,>=0.28.0
Requires-Dist: motor<4.0.0,>=3.6.1
Requires-Dist: fastapi<0.116.0,>=0.115.6
Requires-Dist: uvicorn<0.35.0,>=0.34.0
Requires-Dist: gunicorn==23.0.0
Dynamic: author
Dynamic: author-email
Dynamic: classifier
Dynamic: description
Dynamic: description-content-type
Dynamic: home-page
Dynamic: requires-dist
Dynamic: requires-python
Dynamic: summary
